tableplot/__init__.py
tableplot/tableplot.py
tableplot-0.0.3.dist-info/LICENSE
tableplot-0.0.3.dist-info/METADATA
tableplot-0.0.3.dist-info/WHEEL
tableplot-0.0.3.dist-info/RECORD
