Metadata-Version: 2.3
Name: tableplot
Version: 0.0.3
Summary: A Python tool for creating interactive and dynamic tableplot-style visualizations.
License: MIT
Keywords: tableplot,visualization,data,interactive,plotly,pandas,data analysis
Author: Antonio Rodrigues
Author-email: antonioazam@gmail.com
Requires-Python: >=3.7,<3.14
Classifier: Intended Audience :: Developers
Classifier: Intended Audience :: Science/Research
Classifier: License :: OSI Approved :: MIT License
Classifier: Operating System :: OS Independent
Classifier: Programming Language :: Python :: 3
Classifier: Programming Language :: Python :: 3.7
Classifier: Programming Language :: Python :: 3.8
Classifier: Programming Language :: Python :: 3.9
Classifier: Programming Language :: Python :: 3.10
Classifier: Programming Language :: Python :: 3.11
Classifier: Programming Language :: Python :: 3.12
Classifier: Programming Language :: Python :: 3.13
Classifier: Topic :: Scientific/Engineering :: Visualization
Requires-Dist: numpy (>=1.18.0,<3.0.0)
Requires-Dist: pandas (>=1.0.0,<3.0.0)
Requires-Dist: plotly (>=5.0.0,<7.0.0)
Project-URL: Homepage, https://github.com/antoniorodrigues428/tabplot-python
Project-URL: Repository, https://github.com/antoniorodrigues428/tabplot-python
